autoconf_language_server/__init__.py
autoconf_language_server/__main__.py
autoconf_language_server/_shtab.py
autoconf_language_server/py.typed
autoconf_language_server/server.py
autoconf_language_server/utils.py
autoconf_language_server/assets/json/config.json
autoconf_language_server/misc/__init__.py
autoconf_language_server/misc/autoconf.py
autotools_language_server-0.0.23.data/data/share/bash-completion/completions/autoconf-language-server
autotools_language_server-0.0.23.data/data/share/bash-completion/completions/autotools-language-server
autotools_language_server-0.0.23.data/data/share/bash-completion/completions/make-language-server
autotools_language_server-0.0.23.data/data/share/man/man1/autoconf-language-server.1
autotools_language_server-0.0.23.data/data/share/man/man1/autotools-language-server.1
autotools_language_server-0.0.23.data/data/share/man/man1/make-language-server.1
autotools_language_server-0.0.23.data/data/share/zsh/site-functions/_autoconf-language-server
autotools_language_server-0.0.23.data/data/share/zsh/site-functions/_autotools-language-server
autotools_language_server-0.0.23.data/data/share/zsh/site-functions/_make-language-server
autotools_language_server-0.0.23.dist-info/licenses/LICENSE
make_language_server/__init__.py
make_language_server/__main__.py
make_language_server/_metainfo.py
make_language_server/_shtab.py
make_language_server/_version.py
make_language_server/finders.py
make_language_server/py.typed
make_language_server/server.py
make_language_server/utils.py
make_language_server/assets/json/make.json
make_language_server/assets/queries/define.scm
make_language_server/assets/queries/include.scm
make_language_server/misc/__init__.py
make_language_server/misc/make.py
autotools_language_server-0.0.23.dist-info/METADATA
autotools_language_server-0.0.23.dist-info/WHEEL
autotools_language_server-0.0.23.dist-info/entry_points.txt
autotools_language_server-0.0.23.dist-info/top_level.txt
autotools_language_server-0.0.23.dist-info/RECORD
